ncoop57_mages/__init__.py
ncoop57_mages/_nbdev.py
ncoop57_mages/cli.py
ncoop57_mages/core.py
ncoop57_mages/game.py
ncoop57_mages-0.0.3.dist-info/LICENSE
ncoop57_mages-0.0.3.dist-info/METADATA
ncoop57_mages-0.0.3.dist-info/WHEEL
ncoop57_mages-0.0.3.dist-info/entry_points.txt
ncoop57_mages-0.0.3.dist-info/top_level.txt
ncoop57_mages-0.0.3.dist-info/RECORD
