Metadata-Version: 2.1
Name: ncoop57-mages
Version: 0.0.3
Summary: A description of your project
Home-page: https://github.com/ncoop57/ncoop57_mages/tree/master/
Author: Nathan Cooper
Author-email: nathanallencooper@gmail.com
License: Apache Software License 2.0
Keywords: some keywords
Platform: UNKNOWN
Classifier: Development Status :: 3 - Alpha
Classifier: Intended Audience :: Developers
Classifier: License :: OSI Approved :: Apache Software License
Classifier: Natural Language :: English
Classifier: Programming Language :: Python :: 3.6
Classifier: Programming Language :: Python :: 3.7
Classifier: Programming Language :: Python :: 3.8
Requires-Python: >=3.6
